{"object": {"repositories": {"https://github.com/apple/swift-nio-ssl-support.git": {"repositoryURL": "https://github.com/apple/swift-nio-ssl-support.git", "status": "available", "subpath": "swift-nio-ssl-support.git--4689874318343860737"}, "https://github.com/apple/swift-nio-ssl.git": {"repositoryURL": "https://github.com/apple/swift-nio-ssl.git", "status": "available", "subpath": "swift-nio-ssl.git--2388239779903175492"}, "https://github.com/apple/swift-nio-zlib-support.git": {"repositoryURL": "https://github.com/apple/swift-nio-zlib-support.git", "status": "available", "subpath": "swift-nio-zlib-support.git--1543161702226831453"}, "https://github.com/apple/swift-nio.git": {"repositoryURL": "https://github.com/apple/swift-nio.git", "status": "available", "subpath": "swift-nio.git-3294926370223438420"}, "https://github.com/vapor/console.git": {"repositoryURL": "https://github.com/vapor/console.git", "status": "available", "subpath": "console.git-7838568927587370598"}, "https://github.com/vapor/core.git": {"repositoryURL": "https://github.com/vapor/core.git", "status": "available", "subpath": "core.git--6260703268760342189"}, "https://github.com/vapor/crypto.git": {"repositoryURL": "https://github.com/vapor/crypto.git", "status": "available", "subpath": "crypto.git-2890167508276651876"}, "https://github.com/vapor/database-kit.git": {"repositoryURL": "https://github.com/vapor/database-kit.git", "status": "available", "subpath": "database-kit.git--4914559893512092988"}, "https://github.com/vapor/fluent-postgresql.git": {"repositoryURL": "https://github.com/vapor/fluent-postgresql.git", "status": "available", "subpath": "fluent-postgresql.git-3206284656085908476"}, "https://github.com/vapor/fluent.git": {"repositoryURL": "https://github.com/vapor/fluent.git", "status": "available", "subpath": "fluent.git--1923934348187396296"}, "https://github.com/vapor/http.git": {"repositoryURL": "https://github.com/vapor/http.git", "status": "available", "subpath": "http.git--8726017324301124809"}, "https://github.com/vapor/multipart.git": {"repositoryURL": "https://github.com/vapor/multipart.git", "status": "available", "subpath": "multipart.git-3261661828486421888"}, "https://github.com/vapor/postgresql.git": {"repositoryURL": "https://github.com/vapor/postgresql.git", "status": "available", "subpath": "postgresql.git-741422192339141907"}, "https://github.com/vapor/routing.git": {"repositoryURL": "https://github.com/vapor/routing.git", "status": "available", "subpath": "routing.git--5063342122631973017"}, "https://github.com/vapor/service.git": {"repositoryURL": "https://github.com/vapor/service.git", "status": "available", "subpath": "service.git--3146874890861890628"}, "https://github.com/vapor/sql.git": {"repositoryURL": "https://github.com/vapor/sql.git", "status": "available", "subpath": "sql.git--3745659267352501851"}, "https://github.com/vapor/template-kit.git": {"repositoryURL": "https://github.com/vapor/template-kit.git", "status": "available", "subpath": "template-kit.git-5976702498533882729"}, "https://github.com/vapor/url-encoded-form.git": {"repositoryURL": "https://github.com/vapor/url-encoded-form.git", "status": "available", "subpath": "url-encoded-form.git--2156127758179469724"}, "https://github.com/vapor/validation.git": {"repositoryURL": "https://github.com/vapor/validation.git", "status": "available", "subpath": "validation.git-3009224595617348796"}, "https://github.com/vapor/vapor.git": {"repositoryURL": "https://github.com/vapor/vapor.git", "status": "available", "subpath": "vapor.git--5318115095675753006"}, "https://github.com/vapor/websocket.git": {"repositoryURL": "https://github.com/vapor/websocket.git", "status": "available", "subpath": "websocket.git-8644357352585719124"}}}, "version": 1}